karadoc/__init__.py
karadoc/airflow/__init__.py
karadoc/airflow/conf.py
karadoc/airflow/dag_graph.py
karadoc/airflow/dag_validations.py
karadoc/airflow/task_validations.py
karadoc/airflow/utils.py
karadoc/airflow/validate.py
karadoc/biqguery/__init__.py
karadoc/biqguery/analyze.py
karadoc/cli/__init__.py
karadoc/cli/commands/__init__.py
karadoc/cli/commands/analyze_bq.py
karadoc/cli/commands/analyze_timeline.py
karadoc/cli/commands/build/__init__.py
karadoc/cli/commands/build/package.py
karadoc/cli/commands/check_connections.py
karadoc/cli/commands/check_keys.py
karadoc/cli/commands/find_tables_to_disable.py
karadoc/cli/commands/list.py
karadoc/cli/commands/list_connections.py
karadoc/cli/commands/nonreg.py
karadoc/cli/commands/pull.py
karadoc/cli/commands/quality_check.py
karadoc/cli/commands/run.py
karadoc/cli/commands/show_airflow_dag_graph.py
karadoc/cli/commands/show_graph.py
karadoc/cli/commands/stream.py
karadoc/cli/commands/validate.py
karadoc/cli/commands/validate_airflow.py
karadoc/common/__init__.py
karadoc/common/analyze/__init__.py
karadoc/common/analyze/analyze_job.py
karadoc/common/analyze/draw_timeline_analysis.py
karadoc/common/analyze/timeline_analysis.py
karadoc/common/class_utils.py
karadoc/common/commands/__init__.py
karadoc/common/commands/command.py
karadoc/common/commands/command_group.py
karadoc/common/commands/exec.py
karadoc/common/commands/help.py
karadoc/common/commands/options/__init__.py
karadoc/common/commands/options/dry_option.py
karadoc/common/commands/options/read_from_option.py
karadoc/common/commands/options/spark_conf_option.py
karadoc/common/commands/options/tables_option.py
karadoc/common/commands/options/vars_option.py
karadoc/common/commands/parsing.py
karadoc/common/commands/return_code.py
karadoc/common/commands/spark.py
karadoc/common/commands/utils.py
karadoc/common/conf/__init__.py
karadoc/common/conf/conf_box.py
karadoc/common/conf/configurable_class.py
karadoc/common/conf/keyvault.py
karadoc/common/conf/package.py
karadoc-0.0.3.dist-info/entry_points.txt
karadoc-0.0.3.dist-info/LICENSE
karadoc-0.0.3.dist-info/WHEEL
karadoc-0.0.3.dist-info/METADATA
karadoc-0.0.3.dist-info/RECORD
